seqfold/__init__.py
seqfold/dna.py
seqfold/fold.py
seqfold/main.py
seqfold/rna.py
seqfold/tm.py
seqfold/types.py
seqfold-0.9.0.dist-info/licenses/LICENSE
tests/__init__.py
tests/fold_examples.py
tests/fold_profile.py
tests/fold_test.py
tests/tm_test.py
seqfold-0.9.0.dist-info/METADATA
seqfold-0.9.0.dist-info/WHEEL
seqfold-0.9.0.dist-info/entry_points.txt
seqfold-0.9.0.dist-info/top_level.txt
seqfold-0.9.0.dist-info/RECORD
