Metadata-Version: 2.4
Name: seqfold
Version: 0.9.0
Summary: Predict the minimum free energy structure of nucleic acids
Home-page: https://github.com/Lattice-Automation/seqfold
Author: JJTimmons
Author-email: jtimmons@latticeautomation.com
License: mit
Classifier: Development Status :: 4 - Beta
Classifier: Programming Language :: Python :: 3 :: Only
Classifier: Topic :: Scientific/Engineering :: Bio-Informatics
Classifier: Environment :: Console
Requires-Python: >=3.5
License-File: LICENSE
Provides-Extra: dev
Requires-Dist: black; extra == "dev"
Requires-Dist: pylint; extra == "dev"
Requires-Dist: bumpversion; extra == "dev"
Dynamic: author
Dynamic: author-email
Dynamic: classifier
Dynamic: description
Dynamic: description-content-type
Dynamic: home-page
Dynamic: license
Dynamic: license-file
Dynamic: provides-extra
Dynamic: requires-python
Dynamic: summary
